misho_api/__init__.py
misho_api/hour_slot.py
misho_api/job.py
misho_api/py.typed
misho_api/reservation_calendar.py
misho_api/time_slot.py
misho_api/user.py
misho_api-0.1.0.dist-info/METADATA
misho_api-0.1.0.dist-info/WHEEL
misho_api-0.1.0.dist-info/RECORD
