Metadata-Version: 2.4
Name: misho-api
Version: 0.1.0
Summary: Add your description here
Author-email: Ivo Petkovic <ivo.petkovic@gmail.com>
Requires-Python: >=3.12
Requires-Dist: pydantic
